MANIFEST.in
README.md
setup.py
ren_algorithm/__init__.py
ren_algorithm.egg-info/PKG-INFO
ren_algorithm.egg-info/SOURCES.txt
ren_algorithm.egg-info/dependency_links.txt
ren_algorithm.egg-info/requires.txt
ren_algorithm.egg-info/top_level.txt
ren_algorithm/KNNmodel/__init__.py
ren_algorithm/KNNmodel/knn.py
ren_algorithm/Linearregression/__init__.py
ren_algorithm/Linearregression/linear_regression.py
ren_algorithm/SVM/__init__.py
ren_algorithm/SVM/svm.py
ren_algorithm/XGBoost/__init__.py
ren_algorithm/XGBoost/decision_tree.py
ren_algorithm/XGBoost/xgboost_regression.py
ren_algorithm/decisiontreeclassification/__init__.py
ren_algorithm/decisiontreeclassification/decision_tree.py
ren_algorithm/logisticregression/__init__.py
ren_algorithm/logisticregression/logistic_regression.py
ren_algorithm/randomforest/__init__.py
ren_algorithm/randomforest/decision_tree.py
ren_algorithm/randomforest/random_forest.py