Metadata-Version: 2.2
Name: ren_algorithm
Version: 0.1.5
Summary: A collection of machine learning algorithms
Author: Surendhar
Requires-Python: >=3.6
Requires-Dist: numpy==1.24.1
Dynamic: author
Dynamic: description
Dynamic: description-content-type
Dynamic: requires-dist
Dynamic: requires-python
Dynamic: summary
